garaga-0.18.2.dist-info/METADATA
garaga-0.18.2.dist-info/WHEEL
garaga-0.18.2.dist-info/entry_points.txt
garaga-0.18.2.dist-info/licenses/LICENSE
garaga/algebra.py
garaga/definitions.py
garaga/drand/client.py
garaga/drand/tlock.py
garaga/extension_field_modulo_circuit.py
garaga/garaga_rs.pypy310-pp73-arm-linux-gnu.so
garaga/hints/bls.py
garaga/hints/ecip.py
garaga/hints/eisenstein.py
garaga/hints/extf_mul.py
garaga/hints/fake_glv.py
garaga/hints/frobenius.py
garaga/hints/io.py
garaga/hints/keccak256.py
garaga/hints/multi_miller_witness.py
garaga/hints/neg_3.py
garaga/hints/tower_backup.py
garaga/modulo_circuit.py
garaga/modulo_circuit_structs.py
garaga/poseidon_transcript.py
garaga/precompiled_circuits/all_circuits.py
garaga/precompiled_circuits/cofactor_clearing.py
garaga/precompiled_circuits/compilable_circuits/apply_isogeny.py
garaga/precompiled_circuits/compilable_circuits/base.py
garaga/precompiled_circuits/compilable_circuits/cairo1_mpcheck_circuits.py
garaga/precompiled_circuits/compilable_circuits/cairo1_tower_pairing.py
garaga/precompiled_circuits/compilable_circuits/common_cairo_fustat_circuits.py
garaga/precompiled_circuits/compilable_circuits/ultra_honk.py
garaga/precompiled_circuits/ec.py
garaga/precompiled_circuits/final_exp.py
garaga/precompiled_circuits/fp2.py
garaga/precompiled_circuits/honk.py
garaga/precompiled_circuits/honk_transcript.py
garaga/precompiled_circuits/isogeny.py
garaga/precompiled_circuits/map_to_curve.py
garaga/precompiled_circuits/miller_tower.py
garaga/precompiled_circuits/multi_miller_loop.py
garaga/precompiled_circuits/multi_pairing_check.py
garaga/precompiled_circuits/poseidon_bn254.py
garaga/signature.py
garaga/starknet/cli/declare.py
garaga/starknet/cli/deploy.py
garaga/starknet/cli/gen.py
garaga/starknet/cli/smart_contract_project.py
garaga/starknet/cli/starknet_cli.py
garaga/starknet/cli/utils.py
garaga/starknet/cli/verify.py
garaga/starknet/constants.py
garaga/starknet/groth16_contract_generator/calldata.py
garaga/starknet/groth16_contract_generator/examples/gnark_proof_bn254.json
garaga/starknet/groth16_contract_generator/examples/gnark_public_bn254.json
garaga-0.18.2.dist-info/RECORD
