Metadata-Version: 2.4
Name: garaga
Version: 0.18.2
Classifier: Development Status :: 4 - Beta
Classifier: Intended Audience :: Developers
Classifier: Intended Audience :: Science/Research
Classifier: License :: OSI Approved :: MIT License
Classifier: Programming Language :: Python :: 3
Classifier: Programming Language :: Python :: 3.10
Classifier: Topic :: Security :: Cryptography
Classifier: Topic :: Scientific/Engineering :: Mathematics
Classifier: Topic :: Software Development :: Libraries :: Python Modules
Classifier: Operating System :: OS Independent
Requires-Dist: fastecdsa>=3.0.0
Requires-Dist: sympy
Requires-Dist: typer
Requires-Dist: python-dotenv
Requires-Dist: starknet-py==0.26.2
Requires-Dist: requests
Requires-Dist: filelock
Requires-Dist: maturin ; extra == 'dev'
Requires-Dist: pytest ; extra == 'dev'
Requires-Dist: pytest-asyncio ; extra == 'dev'
Requires-Dist: pytest-xdist ; extra == 'dev'
Requires-Dist: black==24.4.2 ; extra == 'dev'
Requires-Dist: pre-commit ; extra == 'dev'
Requires-Dist: inquirer ; extra == 'dev'
Requires-Dist: pandas ; extra == 'dev'
Requires-Dist: tabulate ; extra == 'dev'
Requires-Dist: hypothesis ; extra == 'dev'
Requires-Dist: rich ; extra == 'dev'
Provides-Extra: dev
License-File: LICENSE
Summary: State-of-the-art Elliptic Curve operations and SNARKS verification for Cairo & Starknet 🐺.
Keywords: elliptic-curves,pairing,zero-knowledge,zk-snarks,zero-knowledge-proofs,zkp,elliptic-curve-cryptography,starks,snarks,cairo-lang,starknet,cryptography,blockchain
Author: feltroidprime, Keep Starknet Strange Contributors
License: MIT
Requires-Python: >=3.10, <3.11
Project-URL: Homepage, https://github.com/keep-starknet-strange/garaga
Project-URL: Repository, https://github.com/keep-starknet-strange/garaga
Project-URL: Documentation, https://garaga.gitbook.io/
Project-URL: Bug Reports, https://github.com/keep-starknet-strange/garaga/issues
Project-URL: Source Code, https://github.com/keep-starknet-strange/garaga
